cenclave/__init__.py
cenclave/error.py
cenclave/log.py
cenclave/main.py
cenclave/command/__init__.py
cenclave/command/helpers.py
cenclave/command/code_provider/__init__.py
cenclave/command/code_provider/decrypt.py
cenclave/command/code_provider/encrypt.py
cenclave/command/code_provider/keygen.py
cenclave/command/code_provider/localtest.py
cenclave/command/code_provider/package.py
cenclave/command/code_provider/scaffold.py
cenclave/command/code_provider/seal.py
cenclave/command/code_provider/unseal.py
cenclave/command/code_provider/verify.py
cenclave/command/sgx_operator/__init__.py
cenclave/command/sgx_operator/evidence.py
cenclave/command/sgx_operator/list_all.py
cenclave/command/sgx_operator/logs.py
cenclave/command/sgx_operator/restart.py
cenclave/command/sgx_operator/run.py
cenclave/command/sgx_operator/spawn.py
cenclave/command/sgx_operator/status.py
cenclave/command/sgx_operator/stop.py
cenclave/command/sgx_operator/test.py
cenclave/common/__init__.py
cenclave/common/helpers.py
cenclave/core/__init__.py
cenclave/core/base64.py
cenclave/core/bootstrap.py
cenclave/core/clock_tick.py
cenclave/core/conf.py
cenclave/core/enclave.py
cenclave/core/fs.py
cenclave/core/ignore_file.py
cenclave/core/no_sgx_docker.py
cenclave/core/sgx_docker.py
cenclave/core/spinner.py
cenclave/core/test_docker.py
cenclave/model/__init__.py
cenclave/model/evidence.py
cenclave/model/package.py
cenclave/template/Dockerfile
cenclave/template/README.md
cenclave/template/config.toml.template
cenclave/template/secrets.json
cenclave/template/secrets_to_seal.json
cenclave/template/src/app.py.template
cenclave/template/src/dotcenclaveignore
cenclave/template/tests/conftest.py.template
cenclave/template/tests/test_app.py.template
cenclave-1.0.0a11.dist-info/METADATA
cenclave-1.0.0a11.dist-info/WHEEL
cenclave-1.0.0a11.dist-info/entry_points.txt
cenclave-1.0.0a11.dist-info/top_level.txt
cenclave-1.0.0a11.dist-info/RECORD
