Metadata-Version: 2.1
Name: cenclave
Version: 1.0.0a11
Summary: Command Line Interface for Cosmian Enclave
Author-email: Cosmian Tech <tech@cosmian.com>
License: MIT
Project-URL: homepage, https://cosmian.com
Project-URL: documentation, https://docs.cosmian.com
Project-URL: repository, https://github.com/Cosmian/cosmian-enclave
Classifier: Development Status :: 5 - Production/Stable
Classifier: Environment :: Console
Classifier: License :: OSI Approved :: MIT License
Classifier: Programming Language :: Python :: 3
Classifier: Programming Language :: Python :: Implementation :: CPython
Requires-Python: >=3.10
Requires-Dist: cryptography<44.0.0,>=43.0.3
Requires-Dist: docker<8.0.0,>=7.1.0
Requires-Dist: intel-sgx-ra<3.0.0,>=2.3.2
Requires-Dist: jinja2<3.2.0,>=3.1.4
Requires-Dist: cenclave-lib-crypto<2.0.0,>=1.0.0
Requires-Dist: pydantic<2.0.0,>=1.10.18
Requires-Dist: pyjwt<3.0.0,>=2.9.0
Requires-Dist: requests<2.33.0,>=2.32.3
Requires-Dist: toml<0.11.0,>=0.10.2
Requires-Dist: urllib3<3.0.0,>=2.2.3
Requires-Dist: importlib-resources<7.0.0,>=6.4.5
Provides-Extra: dev
Requires-Dist: black<25.0.0,>=24.10.0; extra == "dev"
Requires-Dist: isort<6.0.0,>=5.13.2; extra == "dev"
Requires-Dist: pylint<4.0.0,>=3.3.1; extra == "dev"
Requires-Dist: pycodestyle<3.0.0,>=2.12.1; extra == "dev"
Requires-Dist: pydocstyle<7.0.0,>=6.3.0; extra == "dev"
Requires-Dist: mypy<2.0.0,>=1.13.0; extra == "dev"
Requires-Dist: pytest<9.0.0,>=8.3.3; extra == "dev"
Requires-Dist: build<1.3.0,>=1.2.2; extra == "dev"
Requires-Dist: wheel<0.50.0,>=0.45.0; extra == "dev"
Requires-Dist: flask==3.1.0; extra == "dev"
Requires-Dist: types-requests<2.33.0,>=2.32.0; extra == "dev"
Requires-Dist: types-urllib3<1.27.0,>=1.26.0; extra == "dev"
Requires-Dist: types-toml<0.11.0,>=0.10.0; extra == "dev"
Requires-Dist: types-setuptools<76.0.0,>=75.0.0; extra == "dev"
